LICENSE
README.md
pyproject.toml
setup.cfg
setup.py
src/dumpulator/__init__.py
src/dumpulator/details.py
src/dumpulator/dumpulator.py
src/dumpulator/handles.py
src/dumpulator/memory.py
src/dumpulator/modules.py
src/dumpulator/native.py
src/dumpulator/ntdevices.py
src/dumpulator/ntenums.py
src/dumpulator/ntprimitives.py
src/dumpulator/ntstructs.py
src/dumpulator/ntsyscalls.py
src/dumpulator.egg-info/PKG-INFO
src/dumpulator.egg-info/SOURCES.txt
src/dumpulator.egg-info/dependency_links.txt
src/dumpulator.egg-info/requires.txt
src/dumpulator.egg-info/top_level.txt
src/minidump/__amain__.py
src/minidump/__init__.py
src/minidump/__main__.py
src/minidump/_version.py
src/minidump/aminidumpfile.py
src/minidump/aminidumpreader.py
src/minidump/common_structs.py
src/minidump/constants.py
src/minidump/directory.py
src/minidump/exceptions.py
src/minidump/header.py
src/minidump/minidumpfile.py
src/minidump/minidumpreader.py
src/minidump/minidumpshell.py
src/minidump/win_datatypes.py
src/minidump/writer.py
src/minidump/streams/CommentStreamA.py
src/minidump/streams/CommentStreamW.py
src/minidump/streams/ContextStream.py
src/minidump/streams/ExceptionStream.py
src/minidump/streams/FunctionTableStream.py
src/minidump/streams/HandleDataStream.py
src/minidump/streams/HandleOperationListStream.py
src/minidump/streams/JavaScriptDataStream.py
src/minidump/streams/LastReservedStream.py
src/minidump/streams/Memory64ListStream.py
src/minidump/streams/MemoryInfoListStream.py
src/minidump/streams/MemoryListStream.py
src/minidump/streams/MiscInfoStream.py
src/minidump/streams/ModuleListStream.py
src/minidump/streams/ProcessVmCountersStream.py
src/minidump/streams/SystemInfoStream.py
src/minidump/streams/SystemMemoryInfoStream.py
src/minidump/streams/ThreadExListStream.py
src/minidump/streams/ThreadInfoListStream.py
src/minidump/streams/ThreadListStream.py
src/minidump/streams/TokenStream.py
src/minidump/streams/UnloadedModuleListStream.py
src/minidump/streams/__init__.py
src/minidump/utils/__init__.py
src/minidump/utils/createminidump.py
src/minidump/utils/privileges.py
src/minidump/utils/privileges_types.py
src/minidump/utils/winapi/__init__.py
