Metadata-Version: 2.1
Name: dumpulator
Version: 0.2.0
Summary: An easy-to-use library for emulating code in minidump files.
Home-page: https://github.com/mrexodia/dumpulator
Author: Duncan Ogilvie
Author-email: dumpulator@mrexodia.re
License: UNKNOWN
Project-URL: Bug Tracker, https://github.com/mrexodia/dumpulator/issues
Platform: UNKNOWN
Classifier: Programming Language :: Python :: 3
Classifier: License :: OSI Approved :: Boost Software License 1.0 (BSL-1.0)
Classifier: Operating System :: OS Independent
Requires-Python: >=3.9
License-File: LICENSE
